[{"name": "Control Message", "bits": 32, "type": 31}, {"name": "Control Message", "bits": 32, "type": 31}, {"name": "Data1", "bits": 32, "type": 31}, {"name": "Data1", "bits": 32, "type": 31}, {"name": "Data2", "bits": 32, "type": 31}, {"name": "Data2", "bits": 32, "type": 31}, {"name": "Data3", "bits": 32, "type": 31}, {"name": "Data3", "bits": 32, "type": 31}, {"name": "Data4", "bits": 32, "type": 31}, {"name": "Data4", "bits": 32, "type": 31}, {"name": "Data5", "bits": 32, "type": 31}, {"name": "Data5", "bits": 32, "type": 31}, {"name": "Data6", "bits": 32, "type": 31}, {"name": "Data6", "bits": 32, "type": 31}, {"name": "Data7", "bits": 32, "type": 31}, {"name": "Data7", "bits": 32, "type": 31}, {"name": "Data8", "bits": 32, "type": 31}, {"name": "Data8", "bits": 32, "type": 31}, {"name": "Data9", "bits": 32, "type": 31}, {"name": "Data9", "bits": 32, "type": 31}, {"name": "Data10", "bits": 32, "type": 31}, {"name": "Data10", "bits": 32, "type": 31}]
